firestore_wrapper/__init__.py
firestore_wrapper/backup_manager.py
firestore_wrapper/collection_manager.py
firestore_wrapper/core.py
firestore_wrapper/document_manager.py
firestore_wrapper/firestore_base.py
firestore_wrapper/query_manager.py
firestore_wrapper/schema_utils.py
firestore_wrapper/utility_manager.py
firestore_wrapper-0.3.4.dist-info/LICENSE
firestore_wrapper-0.3.4.dist-info/METADATA
firestore_wrapper-0.3.4.dist-info/WHEEL
firestore_wrapper-0.3.4.dist-info/top_level.txt
firestore_wrapper-0.3.4.dist-info/RECORD
