Metadata-Version: 2.1
Name: firestore-wrapper
Version: 0.3.4
Summary: A custom wrapper for Google Firestore.
Home-page: https://github.com/AntonioVentilii/firestore-wrapper
Author: Antonio Ventilii
Author-email: antonioventilii@gmail.com
License: MIT
Project-URL: Source Code, https://github.com/AntonioVentilii/firestore-wrapper
Project-URL: Issue Tracker, https://github.com/AntonioVentilii/firestore-wrapper/issues
Keywords: firestore api wrapper database
Classifier: Programming Language :: Python :: 3
Classifier: License :: OSI Approved :: MIT License
Classifier: Operating System :: OS Independent
Requires-Python: >=3.7
License-File: LICENSE
Requires-Dist: google-cloud-firestore >=2.5.0
Requires-Dist: schema
